{
  "$schema": "https://developer.microsoft.com/json-schemas/fabric/item/report/definition/bookmark/1.4.0/schema.json",
  "displayName": "Reset",
  "name": "6adb7821906ff17dacbc",
  "options": {
    "targetVisualNames": [],
    "suppressDisplay": true
  },
  "explorationState": {
    "version": "1.3",
    "activeSection": "00333d090b834e6247eb",
    "sections": {
      "00333d090b834e6247eb": {
        "visualContainers": {
          "077e1ed330cb6a983304": {
            "singleVisual": {
              "visualType": "card",
              "objects": {},
              "display": {
                "mode": "hidden"
              }
            }
          },
          "0bae9f307ae05d7e43b0": {
            "singleVisual": {
              "visualType": "card",
              "objects": {},
              "display": {
                "mode": "hidden"
              }
            }
          },
          "0eaa810d001cd0273160": {
            "filters": {
              "byExpr": [
                {
                  "name": "42b1eebd3be0e19adff0",
                  "type": "Advanced",
                  "expression": {
                    "Measure": {
                      "Expression": {
                        "SourceRef": {
                          "Entity": "Mesures"
                        }
                      },
                      "Property": "Dernière MAJ"
                    }
                  },
                  "howCreated": 0
                }
              ]
            },
            "singleVisual": {
              "visualType": "card",
              "objects": {}
            }
          },
          "16b3bdc91550250e5021": {
            "filters": {
              "byExpr": [
                {
                  "name": "fb26f0c43421eee66c7e",
                  "type": "Advanced",
                  "expression": {
                    "Measure": {
                      "Expression": {
                        "SourceRef": {
                          "Entity": "Mesures"
                        }
                      },
                      "Property": "Client MoM % Text"
                    }
                  },
                  "howCreated": 0
                }
              ]
            },
            "singleVisual": {
              "visualType": "card",
              "objects": {},
              "display": {
                "mode": "hidden"
              }
            }
          },
          "8baa83cb016674d07191": {
            "filters": {
              "byExpr": [
                {
                  "name": "de9c0af9f74a5214e3f5",
                  "type": "Advanced",
                  "expression": {
                    "Column": {
                      "Expression": {
                        "SourceRef": {
                          "Entity": "Dim_Date"
                        }
                      },
                      "Property": "Date"
                    }
                  },
                  "howCreated": 1
                },
                {
                  "name": "212afd785382921163ad",
                  "type": "Advanced",
                  "expression": {
                    "Measure": {
                      "Expression": {
                        "SourceRef": {
                          "Entity": "Mesures"
                        }
                      },
                      "Property": "Encours Clients"
                    }
                  },
                  "howCreated": 0
                }
              ]
            },
            "singleVisual": {
              "visualType": "cardVisual",
              "objects": {},
              "orderBy": [
                {
                  "Direction": 2,
                  "Expression": {
                    "Measure": {
                      "Expression": {
                        "SourceRef": {
                          "Entity": "Mesures"
                        }
                      },
                      "Property": "Encours Clients"
                    }
                  }
                }
              ]
            }
          },
          "94b69a520aa551c32505": {
            "filters": {
              "byExpr": [
                {
                  "name": "a0785e335aca0d25c046",
                  "type": "Advanced",
                  "expression": {
                    "Measure": {
                      "Expression": {
                        "SourceRef": {
                          "Entity": "Mesures"
                        }
                      },
                      "Property": "Encours Clients"
                    }
                  },
                  "howCreated": 0
                },
                {
                  "name": "a82ef8dd24fae37337e4",
                  "type": "Categorical",
                  "expression": {
                    "Column": {
                      "Expression": {
                        "SourceRef": {
                          "Entity": "Dim_Date"
                        }
                      },
                      "Property": "Month"
                    }
                  },
                  "howCreated": 0
                }
              ]
            },
            "singleVisual": {
              "visualType": "clusteredColumnChart",
              "objects": {},
              "activeProjections": {
                "Category": [
                  {
                    "Column": {
                      "Expression": {
                        "SourceRef": {
                          "Entity": "Dim_Date"
                        }
                      },
                      "Property": "Month"
                    }
                  }
                ]
              }
            }
          },
          "e9130f79164be870b215": {
            "singleVisual": {
              "visualType": "shape",
              "objects": {}
            }
          },
          "2dae00d40d8005ab6933": {
            "filters": {
              "byExpr": [
                {
                  "name": "442eb59a921fc2b4ea87",
                  "type": "Categorical",
                  "expression": {
                    "Column": {
                      "Expression": {
                        "SourceRef": {
                          "Entity": "Dim_Date"
                        }
                      },
                      "Property": "Date"
                    }
                  },
                  "howCreated": 0
                },
                {
                  "name": "6c03fc3123787d178d41",
                  "type": "Advanced",
                  "expression": {
                    "Measure": {
                      "Expression": {
                        "SourceRef": {
                          "Entity": "Mesures"
                        }
                      },
                      "Property": "Résultat Opérationnel"
                    }
                  },
                  "howCreated": 0
                }
              ]
            },
            "singleVisual": {
              "visualType": "clusteredColumnChart",
              "objects": {},
              "activeProjections": {
                "Category": [
                  {
                    "Column": {
                      "Expression": {
                        "SourceRef": {
                          "Entity": "Dim_Date"
                        }
                      },
                      "Property": "Date"
                    }
                  }
                ]
              },
              "display": {
                "mode": "hidden"
              }
            }
          },
          "2fe947fe360c96003099": {
            "filters": {
              "byExpr": [
                {
                  "name": "39b8dc40751ef006a6b0",
                  "type": "Advanced",
                  "expression": {
                    "Measure": {
                      "Expression": {
                        "SourceRef": {
                          "Entity": "Mesures"
                        }
                      },
                      "Property": "Résultat MoM % Text"
                    }
                  },
                  "howCreated": 0
                }
              ]
            },
            "singleVisual": {
              "visualType": "card",
              "objects": {},
              "display": {
                "mode": "hidden"
              }
            }
          },
          "2ff61c905a3e294ae5d8": {
            "filters": {
              "byExpr": [
                {
                  "name": "e72713bfebee01d122be",
                  "type": "Categorical",
                  "expression": {
                    "Column": {
                      "Expression": {
                        "SourceRef": {
                          "Entity": "Dim_Date"
                        }
                      },
                      "Property": "Date"
                    }
                  },
                  "howCreated": 0
                },
                {
                  "name": "eed265b178a68d766d50",
                  "type": "Advanced",
                  "expression": {
                    "Measure": {
                      "Expression": {
                        "SourceRef": {
                          "Entity": "Mesures"
                        }
                      },
                      "Property": "Encours Clients"
                    }
                  },
                  "howCreated": 0
                }
              ]
            },
            "singleVisual": {
              "visualType": "clusteredColumnChart",
              "objects": {},
              "activeProjections": {
                "Category": [
                  {
                    "Column": {
                      "Expression": {
                        "SourceRef": {
                          "Entity": "Dim_Date"
                        }
                      },
                      "Property": "Date"
                    }
                  }
                ]
              },
              "display": {
                "mode": "hidden"
              }
            }
          },
          "3282d5e0e00ca257d230": {
            "singleVisual": {
              "visualType": "shape",
              "objects": {},
              "display": {
                "mode": "hidden"
              }
            }
          },
          "3e9f719f35c607e208ee": {
            "singleVisual": {
              "visualType": "slicer",
              "objects": {
                "merge": {
                  "data": [
                    {
                      "properties": {
                        "mode": {
                          "expr": {
                            "Literal": {
                              "Value": "'Basic'"
                            }
                          }
                        }
                      }
                    }
                  ]
                }
              },
              "activeProjections": {
                "Values": [
                  {
                    "Column": {
                      "Expression": {
                        "SourceRef": {
                          "Entity": "Dim_Date"
                        }
                      },
                      "Property": "Année"
                    }
                  }
                ]
              },
              "display": {
                "mode": "hidden"
              }
            }
          },
          "4139200a2d0207c05062": {
            "filters": {
              "byExpr": [
                {
                  "name": "8686ee3df8b156dea901",
                  "type": "Advanced",
                  "expression": {
                    "Measure": {
                      "Expression": {
                        "SourceRef": {
                          "Entity": "Mesures"
                        }
                      },
                      "Property": "EncoursFourn MoM % Text"
                    }
                  },
                  "howCreated": 0
                }
              ]
            },
            "singleVisual": {
              "visualType": "card",
              "objects": {},
              "display": {
                "mode": "hidden"
              }
            }
          },
          "6dff6065ac9563c54064": {
            "singleVisual": {
              "visualType": "shape",
              "objects": {}
            }
          },
          "8c9b010b980dad1ba133": {
            "filters": {
              "byExpr": [
                {
                  "name": "3a56ca9201e2482332fc",
                  "type": "Advanced",
                  "filter": {
                    "Version": 2,
                    "From": [
                      {
                        "Name": "d",
                        "Entity": "Dim_Date",
                        "Type": 0
                      }
                    ],
                    "Where": [
                      {
                        "Condition": {
                          "Comparison": {
                            "ComparisonKind": 2,
                            "Left": {
                              "Column": {
                                "Expression": {
                                  "SourceRef": {
                                    "Source": "d"
                                  }
                                },
                                "Property": "Date"
                              }
                            },
                            "Right": {
                              "DateSpan": {
                                "Expression": {
                                  "Literal": {
                                    "Value": "datetime'2025-04-01T00:00:00'"
                                  }
                                },
                                "TimeUnit": 5
                              }
                            }
                          }
                        }
                      }
                    ]
                  },
                  "expression": {
                    "Column": {
                      "Expression": {
                        "SourceRef": {
                          "Entity": "Dim_Date"
                        }
                      },
                      "Property": "Date"
                    }
                  },
                  "howCreated": 1
                },
                {
                  "name": "d9e9aa4a03b4aa499daa",
                  "type": "Advanced",
                  "expression": {
                    "Measure": {
                      "Expression": {
                        "SourceRef": {
                          "Entity": "Mesures"
                        }
                      },
                      "Property": "Total Ventes"
                    }
                  },
                  "howCreated": 0
                }
              ]
            },
            "singleVisual": {
              "visualType": "cardVisual",
              "objects": {}
            }
          },
          "cf63ea4aa2b57729ce00": {
            "filters": {
              "byExpr": [
                {
                  "name": "48970c2ef745898db0f1",
                  "type": "Advanced",
                  "expression": {
                    "Measure": {
                      "Expression": {
                        "SourceRef": {
                          "Entity": "Mesures"
                        }
                      },
                      "Property": "Total Ventes"
                    }
                  },
                  "howCreated": 0
                },
                {
                  "name": "1d6850edf2c6096fbc9a",
                  "type": "Categorical",
                  "expression": {
                    "Column": {
                      "Expression": {
                        "SourceRef": {
                          "Entity": "Dim_Date"
                        }
                      },
                      "Property": "Month"
                    }
                  },
                  "howCreated": 0
                }
              ]
            },
            "singleVisual": {
              "visualType": "clusteredColumnChart",
              "objects": {},
              "activeProjections": {
                "Category": [
                  {
                    "Column": {
                      "Expression": {
                        "SourceRef": {
                          "Entity": "Dim_Date"
                        }
                      },
                      "Property": "Month"
                    }
                  }
                ]
              }
            }
          },
          "427fc847ed5bbe209c65": {
            "singleVisual": {
              "visualType": "image",
              "objects": {}
            }
          },
          "4290e075336be04867c4": {
            "filters": {
              "byExpr": [
                {
                  "name": "8b8ed8b161fe7ab3f080",
                  "type": "TopN",
                  "filter": {
                    "Version": 2,
                    "From": [
                      {
                        "Name": "subquery",
                        "Expression": {
                          "Subquery": {
                            "Query": {
                              "Version": 2,
                              "From": [
                                {
                                  "Name": "d",
                                  "Entity": "Dim_Customers",
                                  "Type": 0
                                },
                                {
                                  "Name": "c",
                                  "Entity": "Customer invoices",
                                  "Type": 0
                                }
                              ],
                              "Select": [
                                {
                                  "Column": {
                                    "Expression": {
                                      "SourceRef": {
                                        "Source": "d"
                                      }
                                    },
                                    "Property": "name"
                                  },
                                  "Name": "field"
                                }
                              ],
                              "OrderBy": [
                                {
                                  "Direction": 2,
                                  "Expression": {
                                    "Aggregation": {
                                      "Expression": {
                                        "Column": {
                                          "Expression": {
                                            "SourceRef": {
                                              "Source": "c"
                                            }
                                          },
                                          "Property": "amount"
                                        }
                                      },
                                      "Function": 0
                                    }
                                  }
                                }
                              ],
                              "Top": 5
                            }
                          }
                        },
                        "Type": 2
                      },
                      {
                        "Name": "d",
                        "Entity": "Dim_Customers",
                        "Type": 0
                      }
                    ],
                    "Where": [
                      {
                        "Condition": {
                          "In": {
                            "Expressions": [
                              {
                                "Column": {
                                  "Expression": {
                                    "SourceRef": {
                                      "Source": "d"
                                    }
                                  },
                                  "Property": "name"
                                }
                              }
                            ],
                            "Table": {
                              "SourceRef": {
                                "Source": "subquery"
                              }
                            }
                          }
                        }
                      }
                    ]
                  },
                  "expression": {
                    "Column": {
                      "Expression": {
                        "SourceRef": {
                          "Entity": "Dim_Customers"
                        }
                      },
                      "Property": "name"
                    }
                  },
                  "howCreated": 0
                },
                {
                  "name": "e52d28fdd0cacb049de2",
                  "type": "Categorical",
                  "expression": {
                    "Column": {
                      "Expression": {
                        "SourceRef": {
                          "Entity": "TranchesBalanceAgée"
                        }
                      },
                      "Property": "Tranche"
                    }
                  },
                  "howCreated": 1
                },
                {
                  "name": "afb4a582666a837a8ea6",
                  "type": "Advanced",
                  "filter": {
                    "Version": 2,
                    "From": [
                      {
                        "Name": "d",
                        "Entity": "Dim_Date",
                        "Type": 0
                      }
                    ],
                    "Where": [
                      {
                        "Condition": {
                          "Comparison": {
                            "ComparisonKind": 2,
                            "Left": {
                              "Column": {
                                "Expression": {
                                  "SourceRef": {
                                    "Source": "d"
                                  }
                                },
                                "Property": "Date"
                              }
                            },
                            "Right": {
                              "DateSpan": {
                                "Expression": {
                                  "Literal": {
                                    "Value": "datetime'2025-04-01T00:00:00'"
                                  }
                                },
                                "TimeUnit": 5
                              }
                            }
                          }
                        }
                      }
                    ]
                  },
                  "expression": {
                    "Column": {
                      "Expression": {
                        "SourceRef": {
                          "Entity": "Dim_Date"
                        }
                      },
                      "Property": "Date"
                    }
                  },
                  "howCreated": 1
                },
                {
                  "name": "d30509878a3deeefc82f",
                  "type": "Categorical",
                  "filter": {
                    "Version": 2,
                    "From": [
                      {
                        "Name": "c",
                        "Entity": "Customer invoices",
                        "Type": 0
                      }
                    ],
                    "Where": [
                      {
                        "Condition": {
                          "In": {
                            "Expressions": [
                              {
                                "Column": {
                                  "Expression": {
                                    "SourceRef": {
                                      "Source": "c"
                                    }
                                  },
                                  "Property": "status"
                                }
                              }
                            ],
                            "Values": [
                              [
                                {
                                  "Literal": {
                                    "Value": "'late'"
                                  }
                                }
                              ]
                            ]
                          }
                        }
                      }
                    ]
                  },
                  "expression": {
                    "Column": {
                      "Expression": {
                        "SourceRef": {
                          "Entity": "Customer invoices"
                        }
                      },
                      "Property": "status"
                    }
                  },
                  "howCreated": 1
                },
                {
                  "name": "8c286429298807f794c2",
                  "type": "Advanced",
                  "expression": {
                    "Aggregation": {
                      "Expression": {
                        "Column": {
                          "Expression": {
                            "SourceRef": {
                              "Entity": "Customer invoices"
                            }
                          },
                          "Property": "amount"
                        }
                      },
                      "Function": 0
                    }
                  },
                  "howCreated": 0
                }
              ]
            },
            "singleVisual": {
              "visualType": "donutChart",
              "objects": {},
              "orderBy": [
                {
                  "Direction": 2,
                  "Expression": {
                    "Aggregation": {
                      "Expression": {
                        "Column": {
                          "Expression": {
                            "SourceRef": {
                              "Entity": "Customer invoices"
                            }
                          },
                          "Property": "amount"
                        }
                      },
                      "Function": 0
                    }
                  }
                }
              ]
            }
          },
          "43826fa1e8b2923ad967": {
            "singleVisual": {
              "visualType": "slicer",
              "objects": {
                "merge": {
                  "data": [
                    {
                      "properties": {
                        "mode": {
                          "expr": {
                            "Literal": {
                              "Value": "'Basic'"
                            }
                          }
                        }
                      }
                    }
                  ]
                }
              },
              "activeProjections": {
                "Values": [
                  {
                    "Column": {
                      "Expression": {
                        "SourceRef": {
                          "Entity": "Dim_Date"
                        }
                      },
                      "Property": "Mois"
                    }
                  }
                ]
              },
              "display": {
                "mode": "hidden"
              }
            }
          },
          "47d558a6ac84b3d60e99": {
            "filters": {
              "byExpr": [
                {
                  "name": "461b0c2a7a6731a2980b",
                  "type": "Advanced",
                  "expression": {
                    "Measure": {
                      "Expression": {
                        "SourceRef": {
                          "Entity": "Mesures"
                        }
                      },
                      "Property": "Revenue MoM % Text"
                    }
                  },
                  "howCreated": 0
                }
              ]
            },
            "singleVisual": {
              "visualType": "card",
              "objects": {},
              "display": {
                "mode": "hidden"
              }
            }
          },
          "498fa0fa574694cc43a9": {
            "filters": {
              "byExpr": [
                {
                  "name": "a5f66e87e3d23e4d6021",
                  "type": "Categorical",
                  "expression": {
                    "Column": {
                      "Expression": {
                        "SourceRef": {
                          "Entity": "Dim_Date"
                        }
                      },
                      "Property": "Date"
                    }
                  },
                  "howCreated": 0
                },
                {
                  "name": "b208212eebdeabd85333",
                  "type": "Advanced",
                  "expression": {
                    "Measure": {
                      "Expression": {
                        "SourceRef": {
                          "Entity": "Mesures"
                        }
                      },
                      "Property": "Encours Fournisseurs"
                    }
                  },
                  "howCreated": 0
                }
              ]
            },
            "singleVisual": {
              "visualType": "clusteredColumnChart",
              "objects": {},
              "activeProjections": {
                "Category": [
                  {
                    "Column": {
                      "Expression": {
                        "SourceRef": {
                          "Entity": "Dim_Date"
                        }
                      },
                      "Property": "Date"
                    }
                  }
                ]
              },
              "display": {
                "mode": "hidden"
              }
            }
          },
          "53f455a71844da09d662": {
            "filters": {
              "byExpr": [
                {
                  "name": "23847528f86677ff4cbc",
                  "type": "Advanced",
                  "expression": {
                    "Measure": {
                      "Expression": {
                        "SourceRef": {
                          "Entity": "Mesures"
                        }
                      },
                      "Property": "tresor MoM % Text"
                    }
                  },
                  "howCreated": 0
                }
              ]
            },
            "singleVisual": {
              "visualType": "card",
              "objects": {},
              "display": {
                "mode": "hidden"
              }
            }
          },
          "342ad638b060e76dda14": {
            "filters": {
              "byExpr": [
                {
                  "name": "318812f0b37293079319",
                  "type": "Advanced",
                  "expression": {
                    "Measure": {
                      "Expression": {
                        "SourceRef": {
                          "Entity": "Mesures"
                        }
                      },
                      "Property": "Encours Fournisseurs"
                    }
                  },
                  "howCreated": 0
                },
                {
                  "name": "f847ed6d832ad57d6bc7",
                  "type": "Categorical",
                  "expression": {
                    "Column": {
                      "Expression": {
                        "SourceRef": {
                          "Entity": "Dim_Date"
                        }
                      },
                      "Property": "Month"
                    }
                  },
                  "howCreated": 0
                }
              ]
            },
            "singleVisual": {
              "visualType": "clusteredColumnChart",
              "objects": {},
              "activeProjections": {
                "Category": [
                  {
                    "Column": {
                      "Expression": {
                        "SourceRef": {
                          "Entity": "Dim_Date"
                        }
                      },
                      "Property": "Month"
                    }
                  }
                ]
              }
            }
          },
          "77f85ab8722c9da805ad": {
            "filters": {
              "byExpr": [
                {
                  "name": "c539649d4d96cb600e6b",
                  "type": "Advanced",
                  "expression": {
                    "Column": {
                      "Expression": {
                        "SourceRef": {
                          "Entity": "Dim_Date"
                        }
                      },
                      "Property": "Date"
                    }
                  },
                  "howCreated": 1
                },
                {
                  "name": "3860cb0c3b5da5fd35cd",
                  "type": "Advanced",
                  "expression": {
                    "Measure": {
                      "Expression": {
                        "SourceRef": {
                          "Entity": "Mesures"
                        }
                      },
                      "Property": "Encours Fournisseurs"
                    }
                  },
                  "howCreated": 0
                }
              ]
            },
            "singleVisual": {
              "visualType": "cardVisual",
              "objects": {},
              "orderBy": [
                {
                  "Direction": 2,
                  "Expression": {
                    "Measure": {
                      "Expression": {
                        "SourceRef": {
                          "Entity": "Mesures"
                        }
                      },
                      "Property": "Encours Fournisseurs"
                    }
                  }
                }
              ]
            }
          },
          "985b29c80a1b3ed42778": {
            "singleVisual": {
              "visualType": "shape",
              "objects": {}
            }
          },
          "351a20c65a7a12a25160": {
            "singleVisual": {
              "visualType": "shape",
              "objects": {}
            }
          },
          "0692775946b67d2b01c9": {
            "filters": {
              "byExpr": [
                {
                  "name": "de4b45f66b8cdf17a09e",
                  "type": "Advanced",
                  "filter": {
                    "Version": 2,
                    "From": [
                      {
                        "Name": "d",
                        "Entity": "Dim_Date",
                        "Type": 0
                      }
                    ],
                    "Where": [
                      {
                        "Condition": {
                          "Comparison": {
                            "ComparisonKind": 2,
                            "Left": {
                              "Column": {
                                "Expression": {
                                  "SourceRef": {
                                    "Source": "d"
                                  }
                                },
                                "Property": "Date"
                              }
                            },
                            "Right": {
                              "DateSpan": {
                                "Expression": {
                                  "Literal": {
                                    "Value": "datetime'2025-04-01T00:00:00'"
                                  }
                                },
                                "TimeUnit": 5
                              }
                            }
                          }
                        }
                      }
                    ]
                  },
                  "expression": {
                    "Column": {
                      "Expression": {
                        "SourceRef": {
                          "Entity": "Dim_Date"
                        }
                      },
                      "Property": "Date"
                    }
                  },
                  "howCreated": 1
                },
                {
                  "name": "41f9db7f26c6c524095d",
                  "type": "Advanced",
                  "expression": {
                    "Measure": {
                      "Expression": {
                        "SourceRef": {
                          "Entity": "Mesures"
                        }
                      },
                      "Property": "Résultat Opérationnel"
                    }
                  },
                  "howCreated": 0
                }
              ]
            },
            "singleVisual": {
              "visualType": "cardVisual",
              "objects": {},
              "orderBy": [
                {
                  "Direction": 2,
                  "Expression": {
                    "Measure": {
                      "Expression": {
                        "SourceRef": {
                          "Entity": "Mesures"
                        }
                      },
                      "Property": "Résultat Opérationnel"
                    }
                  }
                }
              ]
            }
          },
          "8e5da767a55097566099": {
            "filters": {
              "byExpr": [
                {
                  "name": "a03375719fc5d6c3e3bb",
                  "type": "Advanced",
                  "expression": {
                    "Measure": {
                      "Expression": {
                        "SourceRef": {
                          "Entity": "Mesures"
                        }
                      },
                      "Property": "Résultat Opérationnel"
                    }
                  },
                  "howCreated": 0
                },
                {
                  "name": "a5a8a6dcda4423b482a8",
                  "type": "Categorical",
                  "expression": {
                    "Column": {
                      "Expression": {
                        "SourceRef": {
                          "Entity": "Dim_Date"
                        }
                      },
                      "Property": "Month"
                    }
                  },
                  "howCreated": 0
                }
              ]
            },
            "singleVisual": {
              "visualType": "clusteredColumnChart",
              "objects": {},
              "activeProjections": {
                "Category": [
                  {
                    "Column": {
                      "Expression": {
                        "SourceRef": {
                          "Entity": "Dim_Date"
                        }
                      },
                      "Property": "Month"
                    }
                  }
                ]
              }
            }
          },
          "7457ed22087a470c6004": {
            "filters": {
              "byExpr": [
                {
                  "name": "4c24edee1643faa4a8da",
                  "type": "Categorical",
                  "expression": {
                    "Column": {
                      "Expression": {
                        "SourceRef": {
                          "Entity": "Dim_Date"
                        }
                      },
                      "Property": "Date"
                    }
                  },
                  "howCreated": 0
                },
                {
                  "name": "e4a543b54a8b19e07dc3",
                  "type": "Advanced",
                  "expression": {
                    "Measure": {
                      "Expression": {
                        "SourceRef": {
                          "Entity": "Mesures"
                        }
                      },
                      "Property": "Total Ventes"
                    }
                  },
                  "howCreated": 0
                }
              ]
            },
            "singleVisual": {
              "visualType": "clusteredColumnChart",
              "objects": {},
              "activeProjections": {
                "Category": [
                  {
                    "Column": {
                      "Expression": {
                        "SourceRef": {
                          "Entity": "Dim_Date"
                        }
                      },
                      "Property": "Date"
                    }
                  }
                ]
              },
              "display": {
                "mode": "hidden"
              }
            }
          },
          "7580abf7106d90c844e7": {
            "singleVisual": {
              "visualType": "textbox",
              "objects": {}
            }
          },
          "1d6e955e408006840c93": {
            "filters": {
              "byExpr": [
                {
                  "name": "a0a5fb18039b48720b55",
                  "type": "Advanced",
                  "expression": {
                    "Column": {
                      "Expression": {
                        "SourceRef": {
                          "Entity": "Dim_Date"
                        }
                      },
                      "Property": "Date"
                    }
                  },
                  "howCreated": 1
                },
                {
                  "name": "ccadca6f8b4e86254671",
                  "type": "Advanced",
                  "expression": {
                    "Measure": {
                      "Expression": {
                        "SourceRef": {
                          "Entity": "Mesures"
                        }
                      },
                      "Property": "Trésorerie"
                    }
                  },
                  "howCreated": 0
                }
              ]
            },
            "singleVisual": {
              "visualType": "cardVisual",
              "objects": {},
              "orderBy": [
                {
                  "Direction": 2,
                  "Expression": {
                    "Measure": {
                      "Expression": {
                        "SourceRef": {
                          "Entity": "Mesures"
                        }
                      },
                      "Property": "Trésorerie"
                    }
                  }
                }
              ]
            }
          },
          "3896dcd85e269a2ab619": {
            "filters": {
              "byExpr": [
                {
                  "name": "a055c2ea387f84410daa",
                  "type": "Advanced",
                  "expression": {
                    "Measure": {
                      "Expression": {
                        "SourceRef": {
                          "Entity": "Mesures"
                        }
                      },
                      "Property": "Trésorerie"
                    }
                  },
                  "howCreated": 0
                },
                {
                  "name": "65029fe7187243e1f1b2",
                  "type": "Categorical",
                  "expression": {
                    "Column": {
                      "Expression": {
                        "SourceRef": {
                          "Entity": "Dim_Date"
                        }
                      },
                      "Property": "Month"
                    }
                  },
                  "howCreated": 0
                }
              ]
            },
            "singleVisual": {
              "visualType": "clusteredColumnChart",
              "objects": {},
              "activeProjections": {
                "Category": [
                  {
                    "Column": {
                      "Expression": {
                        "SourceRef": {
                          "Entity": "Dim_Date"
                        }
                      },
                      "Property": "Month"
                    }
                  }
                ]
              }
            }
          },
          "a63e4870cb4698909880": {
            "singleVisual": {
              "visualType": "shape",
              "objects": {}
            }
          },
          "88ae2eff9b3d03100cb7": {
            "singleVisual": {
              "visualType": "shape",
              "objects": {},
              "display": {
                "mode": "hidden"
              }
            }
          },
          "8ad50d32b5c1bc293d5b": {
            "singleVisual": {
              "visualType": "shape",
              "objects": {},
              "display": {
                "mode": "hidden"
              }
            }
          },
          "8c8a45ae545cead8404c": {
            "filters": {
              "byExpr": [
                {
                  "name": "4200c5fa6bfddd519e59",
                  "type": "Categorical",
                  "expression": {
                    "Column": {
                      "Expression": {
                        "SourceRef": {
                          "Entity": "Dim_Customers"
                        }
                      },
                      "Property": "name"
                    }
                  },
                  "howCreated": 0
                }
              ]
            },
            "singleVisual": {
              "visualType": "slicer",
              "objects": {
                "merge": {
                  "data": [
                    {
                      "properties": {
                        "numericEnd": {
                          "expr": {
                            "Literal": {
                              "Value": "2024D"
                            }
                          }
                        },
                        "mode": {
                          "expr": {
                            "Literal": {
                              "Value": "'Dropdown'"
                            }
                          }
                        }
                      }
                    }
                  ],
                  "selection": [
                    {
                      "properties": {
                        "strictSingleSelect": {
                          "expr": {
                            "Literal": {
                              "Value": "false"
                            }
                          }
                        }
                      }
                    }
                  ]
                }
              },
              "activeProjections": {
                "Values": [
                  {
                    "Column": {
                      "Expression": {
                        "SourceRef": {
                          "Entity": "Dim_Customers"
                        }
                      },
                      "Property": "name"
                    }
                  }
                ]
              },
              "expansionStates": [
                {
                  "roles": [
                    "Values"
                  ],
                  "levels": [
                    {
                      "queryRefs": [
                        "Dim_Customers.name"
                      ],
                      "isCollapsed": true,
                      "isPinned": true
                    }
                  ],
                  "root": {
                    "identityValues": []
                  }
                }
              ]
            }
          },
          "11fd0829228a0045c7c6": {
            "filters": {
              "byExpr": [
                {
                  "name": "be06c7b73f0770df11c8",
                  "type": "Advanced",
                  "expression": {
                    "Measure": {
                      "Expression": {
                        "SourceRef": {
                          "Entity": "Mesures"
                        }
                      },
                      "Property": "Trésorerie Nette"
                    }
                  },
                  "howCreated": 0
                },
                {
                  "name": "a550bc569e778fe0cd19",
                  "type": "Categorical",
                  "expression": {
                    "Column": {
                      "Expression": {
                        "SourceRef": {
                          "Entity": "Dim_Date"
                        }
                      },
                      "Property": "Month"
                    }
                  },
                  "howCreated": 0
                }
              ]
            },
            "singleVisual": {
              "visualType": "clusteredColumnChart",
              "objects": {},
              "activeProjections": {
                "Category": [
                  {
                    "Column": {
                      "Expression": {
                        "SourceRef": {
                          "Entity": "Dim_Date"
                        }
                      },
                      "Property": "Month"
                    }
                  }
                ]
              }
            }
          },
          "81232ef900dda29d522c": {
            "filters": {
              "byExpr": [
                {
                  "name": "4b0e295c8e7ceba41ff1",
                  "type": "Advanced",
                  "expression": {
                    "Column": {
                      "Expression": {
                        "SourceRef": {
                          "Entity": "Dim_Date"
                        }
                      },
                      "Property": "Date"
                    }
                  },
                  "howCreated": 1
                },
                {
                  "name": "b6f52b56c879496d453e",
                  "type": "Advanced",
                  "expression": {
                    "Measure": {
                      "Expression": {
                        "SourceRef": {
                          "Entity": "Mesures"
                        }
                      },
                      "Property": "Trésorerie Nette"
                    }
                  },
                  "howCreated": 0
                }
              ]
            },
            "singleVisual": {
              "visualType": "cardVisual",
              "objects": {},
              "orderBy": [
                {
                  "Direction": 2,
                  "Expression": {
                    "Measure": {
                      "Expression": {
                        "SourceRef": {
                          "Entity": "Mesures"
                        }
                      },
                      "Property": "Trésorerie Nette"
                    }
                  }
                }
              ]
            }
          },
          "96fec69642ddb95da147": {
            "singleVisual": {
              "visualType": "shape",
              "objects": {}
            }
          },
          "9b866480710706804600": {
            "singleVisual": {
              "visualType": "image",
              "objects": {},
              "display": {
                "mode": "hidden"
              }
            }
          },
          "9d931c5f0273086cca3c": {
            "singleVisual": {
              "visualType": "card",
              "objects": {},
              "display": {
                "mode": "hidden"
              }
            }
          },
          "a9792740608c72b5e381": {
            "singleVisual": {
              "visualType": "card",
              "objects": {},
              "display": {
                "mode": "hidden"
              }
            }
          },
          "abf4fb78e00bd90a35d1": {
            "filters": {
              "byExpr": [
                {
                  "name": "ce4aa34a0adbe0f0347c",
                  "type": "Categorical",
                  "filter": {
                    "Version": 2,
                    "From": [
                      {
                        "Name": "d",
                        "Entity": "Dim_Date",
                        "Type": 0
                      }
                    ],
                    "Where": [
                      {
                        "Condition": {
                          "In": {
                            "Expressions": [
                              {
                                "Column": {
                                  "Expression": {
                                    "SourceRef": {
                                      "Source": "d"
                                    }
                                  },
                                  "Property": "Afficher_12M_Glissants"
                                }
                              }
                            ],
                            "Values": [
                              [
                                {
                                  "Literal": {
                                    "Value": "1L"
                                  }
                                }
                              ]
                            ]
                          }
                        }
                      }
                    ]
                  },
                  "expression": {
                    "Column": {
                      "Expression": {
                        "SourceRef": {
                          "Entity": "Dim_Date"
                        }
                      },
                      "Property": "Afficher_12M_Glissants"
                    }
                  },
                  "howCreated": 1
                },
                {
                  "name": "c595a7e0f0fc5d9e5e85",
                  "type": "Advanced",
                  "expression": {
                    "Measure": {
                      "Expression": {
                        "SourceRef": {
                          "Entity": "Mesures"
                        }
                      },
                      "Property": "CA"
                    }
                  },
                  "howCreated": 0
                },
                {
                  "name": "1d644f4f8abd08a2c861",
                  "type": "Advanced",
                  "expression": {
                    "Measure": {
                      "Expression": {
                        "SourceRef": {
                          "Entity": "Mesures"
                        }
                      },
                      "Property": "Charges"
                    }
                  },
                  "howCreated": 0
                },
                {
                  "name": "55c4690c02f3eaa23502",
                  "type": "Advanced",
                  "expression": {
                    "Measure": {
                      "Expression": {
                        "SourceRef": {
                          "Entity": "Mesures"
                        }
                      },
                      "Property": "Resultat Cumulées(M)"
                    }
                  },
                  "howCreated": 0
                },
                {
                  "name": "18f321c7f0dffddfd674",
                  "type": "Categorical",
                  "expression": {
                    "Column": {
                      "Expression": {
                        "SourceRef": {
                          "Entity": "Dim_Date"
                        }
                      },
                      "Property": "Year-Month"
                    }
                  },
                  "howCreated": 0
                }
              ]
            },
            "singleVisual": {
              "visualType": "lineChart",
              "objects": {},
              "orderBy": [
                {
                  "Direction": 1,
                  "Expression": {
                    "Column": {
                      "Expression": {
                        "SourceRef": {
                          "Entity": "Dim_Date"
                        }
                      },
                      "Property": "Année-Mois"
                    }
                  }
                }
              ],
              "activeProjections": {
                "Category": [
                  {
                    "Column": {
                      "Expression": {
                        "SourceRef": {
                          "Entity": "Dim_Date"
                        }
                      },
                      "Property": "Year-Month"
                    }
                  }
                ]
              }
            }
          },
          "b8f808704358c5607088": {
            "filters": {
              "byExpr": [
                {
                  "name": "9ef07f05a38ee896e63d",
                  "type": "Advanced",
                  "filter": {
                    "Version": 2,
                    "From": [
                      {
                        "Name": "c",
                        "Entity": "Customer invoices",
                        "Type": 0
                      }
                    ],
                    "Where": [
                      {
                        "Condition": {
                          "Comparison": {
                            "ComparisonKind": 1,
                            "Left": {
                              "Aggregation": {
                                "Expression": {
                                  "Column": {
                                    "Expression": {
                                      "SourceRef": {
                                        "Source": "c"
                                      }
                                    },
                                    "Property": "amount"
                                  }
                                },
                                "Function": 0
                              }
                            },
                            "Right": {
                              "Literal": {
                                "Value": "0L"
                              }
                            }
                          }
                        }
                      }
                    ]
                  },
                  "expression": {
                    "Aggregation": {
                      "Expression": {
                        "Column": {
                          "Expression": {
                            "SourceRef": {
                              "Entity": "Customer invoices"
                            }
                          },
                          "Property": "amount"
                        }
                      },
                      "Function": 0
                    }
                  },
                  "howCreated": 0
                },
                {
                  "name": "fabf232c394791472802",
                  "type": "Categorical",
                  "filter": {
                    "Version": 2,
                    "From": [
                      {
                        "Name": "c",
                        "Entity": "Customer invoices",
                        "Type": 0
                      }
                    ],
                    "Where": [
                      {
                        "Condition": {
                          "In": {
                            "Expressions": [
                              {
                                "Column": {
                                  "Expression": {
                                    "SourceRef": {
                                      "Source": "c"
                                    }
                                  },
                                  "Property": "status"
                                }
                              }
                            ],
                            "Values": [
                              [
                                {
                                  "Literal": {
                                    "Value": "'upcoming'"
                                  }
                                }
                              ]
                            ]
                          }
                        }
                      }
                    ]
                  },
                  "expression": {
                    "Column": {
                      "Expression": {
                        "SourceRef": {
                          "Entity": "Customer invoices"
                        }
                      },
                      "Property": "status"
                    }
                  },
                  "howCreated": 1
                },
                {
                  "name": "baf4e59e2c56090df5a3",
                  "type": "Categorical",
                  "expression": {
                    "Column": {
                      "Expression": {
                        "SourceRef": {
                          "Entity": "Dim_Customers"
                        }
                      },
                      "Property": "name"
                    }
                  },
                  "howCreated": 0
                }
              ]
            },
            "singleVisual": {
              "visualType": "clusteredColumnChart",
              "objects": {},
              "orderBy": [
                {
                  "Direction": 2,
                  "Expression": {
                    "Aggregation": {
                      "Expression": {
                        "Column": {
                          "Expression": {
                            "SourceRef": {
                              "Entity": "Customer invoices"
                            }
                          },
                          "Property": "amount"
                        }
                      },
                      "Function": 0
                    }
                  }
                }
              ],
              "activeProjections": {
                "Category": [
                  {
                    "Column": {
                      "Expression": {
                        "SourceRef": {
                          "Entity": "Dim_Customers"
                        }
                      },
                      "Property": "name"
                    }
                  }
                ]
              }
            }
          },
          "c73340960ebd2255ae4e": {
            "filters": {
              "byExpr": [
                {
                  "name": "f3c9947d49950bad3373",
                  "type": "Categorical",
                  "expression": {
                    "Column": {
                      "Expression": {
                        "SourceRef": {
                          "Entity": "Dim_Date"
                        }
                      },
                      "Property": "Date"
                    }
                  },
                  "howCreated": 0
                },
                {
                  "name": "7bae86c6a02dbc654ef8",
                  "type": "Advanced",
                  "expression": {
                    "Measure": {
                      "Expression": {
                        "SourceRef": {
                          "Entity": "Mesures"
                        }
                      },
                      "Property": "Trésorerie"
                    }
                  },
                  "howCreated": 0
                }
              ]
            },
            "singleVisual": {
              "visualType": "clusteredColumnChart",
              "objects": {},
              "activeProjections": {
                "Category": [
                  {
                    "Column": {
                      "Expression": {
                        "SourceRef": {
                          "Entity": "Dim_Date"
                        }
                      },
                      "Property": "Date"
                    }
                  }
                ]
              },
              "display": {
                "mode": "hidden"
              }
            }
          },
          "ca943ce418b55d9ac2ce": {
            "filters": {
              "byExpr": [
                {
                  "name": "0b8d7316ebe92db55c22",
                  "type": "Categorical",
                  "filter": {
                    "Version": 2,
                    "From": [
                      {
                        "Name": "c",
                        "Entity": "Customer invoices",
                        "Type": 0
                      }
                    ],
                    "Where": [
                      {
                        "Condition": {
                          "In": {
                            "Expressions": [
                              {
                                "Column": {
                                  "Expression": {
                                    "SourceRef": {
                                      "Source": "c"
                                    }
                                  },
                                  "Property": "status"
                                }
                              }
                            ],
                            "Values": [
                              [
                                {
                                  "Literal": {
                                    "Value": "'late'"
                                  }
                                }
                              ],
                              [
                                {
                                  "Literal": {
                                    "Value": "'upcoming'"
                                  }
                                }
                              ]
                            ]
                          }
                        }
                      }
                    ]
                  },
                  "expression": {
                    "Column": {
                      "Expression": {
                        "SourceRef": {
                          "Entity": "Customer invoices"
                        }
                      },
                      "Property": "status"
                    }
                  },
                  "howCreated": 1
                },
                {
                  "name": "42e487326db29c9e7931",
                  "type": "Categorical",
                  "expression": {
                    "Column": {
                      "Expression": {
                        "SourceRef": {
                          "Entity": "Dim_Suppliers"
                        }
                      },
                      "Property": "name"
                    }
                  },
                  "howCreated": 1
                },
                {
                  "name": "3787be3c67cfed094f53",
                  "type": "Categorical",
                  "filter": {
                    "Version": 2,
                    "From": [
                      {
                        "Name": "c",
                        "Entity": "Customer invoices",
                        "Type": 0
                      }
                    ],
                    "Where": [
                      {
                        "Condition": {
                          "In": {
                            "Expressions": [
                              {
                                "Column": {
                                  "Expression": {
                                    "SourceRef": {
                                      "Source": "c"
                                    }
                                  },
                                  "Property": "paid"
                                }
                              }
                            ],
                            "Values": [
                              [
                                {
                                  "Literal": {
                                    "Value": "false"
                                  }
                                }
                              ]
                            ]
                          }
                        }
                      }
                    ]
                  },
                  "expression": {
                    "Column": {
                      "Expression": {
                        "SourceRef": {
                          "Entity": "Customer invoices"
                        }
                      },
                      "Property": "paid"
                    }
                  },
                  "howCreated": 1
                },
                {
                  "name": "e3ed18c6030459b50ea4",
                  "type": "Advanced",
                  "expression": {
                    "Aggregation": {
                      "Expression": {
                        "Column": {
                          "Expression": {
                            "SourceRef": {
                              "Entity": "Supplier invoices"
                            }
                          },
                          "Property": "amount"
                        }
                      },
                      "Function": 0
                    }
                  },
                  "howCreated": 1
                },
                {
                  "name": "0bcdc52c510c3d70883f",
                  "type": "Categorical",
                  "expression": {
                    "Column": {
                      "Expression": {
                        "SourceRef": {
                          "Entity": "TranchesBalanceAgée"
                        }
                      },
                      "Property": "Tranche"
                    }
                  },
                  "howCreated": 0
                },
                {
                  "name": "1bcbd07b000da793bc2f",
                  "type": "Advanced",
                  "expression": {
                    "Aggregation": {
                      "Expression": {
                        "Column": {
                          "Expression": {
                            "SourceRef": {
                              "Entity": "Customer invoices"
                            }
                          },
                          "Property": "amount"
                        }
                      },
                      "Function": 0
                    }
                  },
                  "howCreated": 0
                }
              ]
            },
            "singleVisual": {
              "visualType": "columnChart",
              "objects": {},
              "activeProjections": {
                "Category": [
                  {
                    "Column": {
                      "Expression": {
                        "SourceRef": {
                          "Entity": "TranchesBalanceAgée"
                        }
                      },
                      "Property": "Tranche"
                    }
                  }
                ]
              }
            }
          },
          "cf3a8200035ddab08a23": {
            "singleVisual": {
              "visualType": "actionButton",
              "objects": {},
              "display": {
                "mode": "hidden"
              }
            }
          },
          "d5d817813b9294149b10": {
            "filters": {
              "byExpr": [
                {
                  "name": "4796efd8ed20e71d4f46",
                  "type": "Categorical",
                  "expression": {
                    "Column": {
                      "Expression": {
                        "SourceRef": {
                          "Entity": "Period Slicer"
                        }
                      },
                      "Property": "Period"
                    }
                  },
                  "howCreated": 0
                }
              ]
            },
            "singleVisual": {
              "visualType": "slicer",
              "objects": {
                "merge": {
                  "general": [
                    {
                      "properties": {
                        "filter": {
                          "filter": {
                            "Version": 2,
                            "From": [
                              {
                                "Name": "p",
                                "Entity": "Period Slicer",
                                "Type": 0
                              }
                            ],
                            "Where": [
                              {
                                "Condition": {
                                  "In": {
                                    "Expressions": [
                                      {
                                        "Column": {
                                          "Expression": {
                                            "SourceRef": {
                                              "Source": "p"
                                            }
                                          },
                                          "Property": "Period"
                                        }
                                      }
                                    ],
                                    "Values": [
                                      [
                                        {
                                          "Literal": {
                                            "Value": "'Current fiscal year'"
                                          }
                                        }
                                      ]
                                    ]
                                  }
                                }
                              }
                            ]
                          }
                        }
                      }
                    }
                  ],
                  "data": [
                    {
                      "properties": {
                        "numericEnd": {
                          "expr": {
                            "Literal": {
                              "Value": "2024D"
                            }
                          }
                        },
                        "mode": {
                          "expr": {
                            "Literal": {
                              "Value": "'Dropdown'"
                            }
                          }
                        }
                      }
                    }
                  ],
                  "selection": [
                    {
                      "properties": {
                        "strictSingleSelect": {
                          "expr": {
                            "Literal": {
                              "Value": "true"
                            }
                          }
                        }
                      }
                    }
                  ]
                }
              },
              "activeProjections": {
                "Values": [
                  {
                    "Column": {
                      "Expression": {
                        "SourceRef": {
                          "Entity": "Period Slicer"
                        }
                      },
                      "Property": "Period"
                    }
                  }
                ]
              }
            }
          },
          "de1eb9e182799ed6377e": {
            "singleVisual": {
              "visualType": "card",
              "objects": {},
              "display": {
                "mode": "hidden"
              }
            }
          },
          "deb96957154b90d813ec": {
            "singleVisual": {
              "visualType": "image",
              "objects": {}
            }
          },
          "e3d4567f0959a7857727": {
            "singleVisual": {
              "visualType": "image",
              "objects": {}
            }
          },
          "e8e80c6da3069c2e7796": {
            "singleVisual": {
              "visualType": "shape",
              "objects": {},
              "display": {
                "mode": "hidden"
              }
            }
          },
          "ec9ffbc756883ac815ee": {
            "singleVisual": {
              "visualType": "shape",
              "objects": {},
              "display": {
                "mode": "hidden"
              }
            }
          },
          "fb81557ec7398db1be1b": {
            "singleVisual": {
              "visualType": "shape",
              "objects": {}
            }
          }
        }
      }
    },
    "objects": {
      "merge": {
        "outspacePane": [
          {
            "properties": {
              "expanded": {
                "expr": {
                  "Literal": {
                    "Value": "true"
                  }
                }
              },
              "visible": {
                "expr": {
                  "Literal": {
                    "Value": "false"
                  }
                }
              }
            }
          }
        ]
      }
    }
  }
}